MANIFEST.in
README.rst
setup.py
aliyun_python_sdk_r_kvstore_test.egg-info/PKG-INFO
aliyun_python_sdk_r_kvstore_test.egg-info/SOURCES.txt
aliyun_python_sdk_r_kvstore_test.egg-info/dependency_links.txt
aliyun_python_sdk_r_kvstore_test.egg-info/requires.txt
aliyun_python_sdk_r_kvstore_test.egg-info/top_level.txt
aliyunsdkr_kvstore/__init__.py
aliyunsdkr_kvstore/request/__init__.py
aliyunsdkr_kvstore/request/v20150101/ActivateInstanceRequest.py
aliyunsdkr_kvstore/request/v20150101/AllocateInstancePublicConnectionRequest.py
aliyunsdkr_kvstore/request/v20150101/AppendReplicaInstanceRequest.py
aliyunsdkr_kvstore/request/v20150101/CreateAccountRequest.py
aliyunsdkr_kvstore/request/v20150101/CreateBackupRequest.py
aliyunsdkr_kvstore/request/v20150101/CreateCacheAnalysisTaskRequest.py
aliyunsdkr_kvstore/request/v20150101/CreateInstanceReplicaRequest.py
aliyunsdkr_kvstore/request/v20150101/CreateInstanceRequest.py
aliyunsdkr_kvstore/request/v20150101/CreateInstancesRequest.py
aliyunsdkr_kvstore/request/v20150101/CreateSnapshotRequest.py
aliyunsdkr_kvstore/request/v20150101/CreateStaticVerificationRequest.py
aliyunsdkr_kvstore/request/v20150101/CreateTempInstanceRequest.py
aliyunsdkr_kvstore/request/v20150101/DataOperateRequest.py
aliyunsdkr_kvstore/request/v20150101/DeactivateInstanceRequest.py
aliyunsdkr_kvstore/request/v20150101/DeleteAccountRequest.py
aliyunsdkr_kvstore/request/v20150101/DeleteInstanceRequest.py
aliyunsdkr_kvstore/request/v20150101/DeleteSnapshotRequest.py
aliyunsdkr_kvstore/request/v20150101/DeleteSnapshotSettingsRequest.py
aliyunsdkr_kvstore/request/v20150101/DeleteTempInstanceRequest.py
aliyunsdkr_kvstore/request/v20150101/DescribeAccountsRequest.py
aliyunsdkr_kvstore/request/v20150101/DescribeActiveOperationTaskCountRequest.py
aliyunsdkr_kvstore/request/v20150101/DescribeActiveOperationTaskRegionRequest.py
aliyunsdkr_kvstore/request/v20150101/DescribeActiveOperationTaskRequest.py
aliyunsdkr_kvstore/request/v20150101/DescribeActiveOperationTaskTypeRequest.py
aliyunsdkr_kvstore/request/v20150101/DescribeAuditRecordsRequest.py
aliyunsdkr_kvstore/request/v20150101/DescribeAvailableResourceRequest.py
aliyunsdkr_kvstore/request/v20150101/DescribeBackupPolicyRequest.py
aliyunsdkr_kvstore/request/v20150101/DescribeBackupsRequest.py
